[
  {
    "id": 1,
    "title": "World Largest Foo Created in Foobar Event",
    "description": "des",
    "user": "Baz Caz",
    "user_image": "res/raw/video_image1.png",
    "category": "Gaming",
    "publication_date": 1717082000419,
    "icon": "video_image1.png",
    "video": "video1",
    "views": 200000000,
    "like": 200,
    "dislike": 1,
    "comments": [
      {
        "id": 1,
        "title": "World Largest Foo Created in Foobar Event",
        "user": "Baz Caz",
        "date": 1717082000419,
        "icon": "video_image1.png"
      }
    ]
  },
  {
    "id": 2,
    "title": "World Largest Foo Created in Foobar Event, prize given",
    "description": "des",
    "user": "Baz Caz",
    "user_image": "video_image1.png",
    "category": "Gaming",
    "publication_date": 1717082000419,
    "icon": "video_image2.png",
    "video": "video2.mp4",
    "views": 200000,
    "like": 200,
    "dislike": 1,
    "comments": [
      {
        "id": 1,
        "title": "World Largest Foo Created in Foobar Event",
        "user": "Baz Caz",
        "date": 1717082000419,
        "icon": "video_image1.png"
      }
    ]
  },
  {
    "id": 3,
    "title": "World Largest Foo Created in Foobar Event",
    "description": "des",
    "user": "Baz Caz",
    "user_image": "video_image1.png",
    "category": "Gaming",
    "publication_date": 1717082000419,
    "icon": "video_image3.png",
    "video": "video3.mp4",
    "views": 200000,
    "like": 200,
    "dislike": 1,
    "comments": [
      {
        "id": 1,
        "title": "World Largest Foo Created in Foobar Event",
        "user": "Baz Caz",
        "date": 1717082000419,
        "icon": "video_image1.png"
      }
    ]
  },
  {
    "id": 4,
    "title": "World Largest Foo Created in Foobar Event",
    "description": "des",
    "user": "Baz Caz",
    "user_image": "video_image1.png",
    "category": "Mixes",
    "publication_date": 1717082000419,
    "icon": "video_image4.png",
    "video": "video4.mp4",
    "views": 200000,
    "like": 200,
    "dislike": 1,
    "comments": [
      {
        "id": 1,
        "title": "World Largest Foo Created in Foobar Event",
        "user": "Baz Caz",
        "date": 1717082000419,
        "icon": "video_image1.png"
      }
    ]
  },
  {
    "id": 5,
    "title": "World Largest Foo Created in Foobar Event",
    "description": "des",
    "user": "Baz Caz",
    "user_image": "video_image1.png",
    "category": "Inventions",
    "publication_date": 1717082000419,
    "icon": "video_image5.png",
    "video": "video5.mp4",
    "views": 200000,
    "like": 200,
    "dislike": 1,
    "comments": [
      {
        "id": 1,
        "title": "World Largest Foo Created in Foobar Event",
        "user": "Baz Caz",
        "date": 1717082000419,
        "icon": "video_image1.png"
      }
    ]
  },
  {
    "id": 6,
    "title": "World Largest Foo Created in Foobar Event",
    "description": "des",
    "user": "Baz Caz",
    "user_image": "video_image1.png",
    "category": "Gaming",
    "publication_date": 1717082000419,
    "icon": "video_image6.png",
    "video": "video6.mp4",
    "views": 200000,
    "like": 200,
    "dislike": 1,
    "comments": [
      {
        "id": 1,
        "title": "World Largest Foo Created in Foobar Event",
        "user": "Baz Caz",
        "date": 1717082000419,
        "icon": "video_image1.png"
      }
    ]
  },
  {
    "id": 7,
    "title": "World Largest Foo Created in Foobar Event",
    "description": "des",
    "user": "Baz Caz",
    "user_image": "res/raw/video_image1.png",
    "category": "Music",
    "publication_date": 1717082000419,
    "icon": "video_image7.png",
    "video": "res/raw/video7.mp4",
    "views": 200000,
    "like": 200,
    "dislike": 1,
    "comments": [
      {
        "id": 1,
        "title": "World Largest Foo Created in Foobar Event",
        "user": "Baz Caz",
        "date": 1717082000419,
        "icon": "video_image1.png"
      }
    ]
  },
  {
    "id": 8,
    "title": "World Largest Foo Created in Foobar Event",
    "description": "des",
    "user": "Baz Caz",
    "user_image": "res/raw/video_image1.png",
    "category": "Gaming",
    "publication_date": 1717082000419,
    "icon": "video_image8.png",
    "video": "video8.mp4",
    "views": 200000,
    "like": 200,
    "dislike": 1,
    "comments": [
      {
        "id": 1,
        "title": "World Largest Foo Created in Foobar Event",
        "user": "Baz Caz",
        "date": 1717082000419,
        "icon": "video_image1.png"
      }
    ]
  },
  {
    "id": 9,
    "title": "World Largest Foo Created in Foobar Event",
    "description": "des",
    "user": "Baz Caz",
    "user_image": "video_image1.png",
    "category": "News",
    "publication_date": 1717082000419,
    "icon": "video_image9.png",
    "video": "video9.mp4",
    "views": 200000,
    "like": 200,
    "dislike": 1,
    "comments": [
      {
        "id": 1,
        "title": "World Largest Foo Created in Foobar Event",
        "user": "Baz Caz",
        "date": 1717082000419,
        "icon": "video_image1.png"
      }
    ]
  },
  {
    "id": 10,
    "title": "World Largest Foo Created in Foobar Event",
    "description": "des",
    "user": "Baz Caz",
    "user_image": "res/raw/video_image1.png",
    "category": "News",
    "publication_date": 1717082000419,
    "icon": "video_image10.png",
    "video": "video10.mp4",
    "views": 200000,
    "like": 200,
    "dislike": 1,
    "comments": [
      {
        "id": 1,
        "title": "World Largest Foo Created in Foobar Event",
        "user": "Baz Caz",
        "date": 1717082000419,
        "icon": "video_image1.png"
      }
    ]
  },
  {
    "id": 11,
    "title": "World Largest Foo Created in Foobar Event",
    "description": "des",
    "user": "Baz Caz",
    "user_image": "video_image1.png",
    "category": "Mixes",
    "publication_date": 1717082000419,
    "icon": "video_image11.png",
    "video": "video11.mp4",
    "views": 200000,
    "like": 200,
    "dislike": 1,
    "comments": [
      {
        "id": 1,
        "title": "World Largest Foo Created in Foobar Event",
        "user": "Baz Caz",
        "date": 1717082000419,
        "icon": "video_image1.png"
      }
    ]
  }
]